mcp_simple_tool/__init__.py
mcp_simple_tool/__main__.py
mcp_simple_tool/server.py
mseep_mcp_simple_tool-1.2.4.dist-info/METADATA
mseep_mcp_simple_tool-1.2.4.dist-info/WHEEL
mseep_mcp_simple_tool-1.2.4.dist-info/entry_points.txt
mseep_mcp_simple_tool-1.2.4.dist-info/RECORD
