Metadata-Version: 2.4
Name: mseep-mcp-simple-tool
Version: 1.2.4
Summary: A simple MCP server exposing a website fetching tool
Author-email: mseep <support@skydeck.ai>
Maintainer-email: David Soria Parra <davidsp@anthropic.com>, Justin Spahr-Summers <justin@anthropic.com>
License: MIT
Keywords: automation,fetch,llm,mcp,web
Classifier: Development Status :: 4 - Beta
Classifier: Intended Audience :: Developers
Classifier: License :: OSI Approved :: MIT License
Classifier: Programming Language :: Python :: 3
Classifier: Programming Language :: Python :: 3.10
Requires-Python: >=3.10
Requires-Dist: anyio>=4.5
Requires-Dist: click>=8.1.0
Requires-Dist: httpx>=0.27
Requires-Dist: mcp
